python_fu/__init__.py
python_fu/commandline.py
python_fu/compat.py
python_fu/helpers.py
python_fu/module.py
python_fu/commands/__init__.py
python_fu/commands/demote.py
python_fu/commands/lsmodules.py
python_fu/commands/mkmodule.py
python_fu/commands/promote.py
python_fu-0.2.2.dist-info/DESCRIPTION.rst
python_fu-0.2.2.dist-info/entry_points.txt
python_fu-0.2.2.dist-info/METADATA
python_fu-0.2.2.dist-info/metadata.json
python_fu-0.2.2.dist-info/RECORD
python_fu-0.2.2.dist-info/top_level.txt
python_fu-0.2.2.dist-info/WHEEL
tests/__init__.py
tests/helpers.py
tests/test_create.py
tests/test_demote.py
tests/test_module.py
tests/test_promote.py
