Metadata-Version: 2.0
Name: python-fu
Version: 0.2.2
Summary: 
Requires-Dist: click (>=4.0)
Requires-Dist: more-itertools
Requires-Dist: pathlib
